UTF_8/__init__.py
UTF_8/vit4.py
UTF_8/pyperclip/__init__.py
UTF_8/pyperclip/__main__.py
dokr_pkg/__init__.py
dokr_pkg/anonymous_matlab.py
dokr_pkg/try1.py
dokr_pkg/vit2.py
dokr_pkg/vit3.py
dokr_pkg/pyperclip/__init__.py
dokr_pkg/pyperclip/__main__.py
vit4.py-0.1.data/scripts/abc_matlab.py
vit4.py-0.1.data/scripts/anonymous_matlab.py
vit4.py-0.1.data/scripts/try1.py
vit4.py-0.1.data/scripts/vit1.py
vit4.py-0.1.data/scripts/vit2.py
vit4.py-0.1.data/scripts/vit3.py
vit4.py-0.1.data/scripts/vit4.py
vit4.py-0.1.dist-info/METADATA
vit4.py-0.1.dist-info/WHEEL
vit4.py-0.1.dist-info/top_level.txt
vit4.py-0.1.dist-info/RECORD
